LICENSE
README.md
setup.py
FlippitTikTokLive/__init__.py
FlippitTikTokLive/utilities.py
FlippitTikTokLive.egg-info/PKG-INFO
FlippitTikTokLive.egg-info/SOURCES.txt
FlippitTikTokLive.egg-info/dependency_links.txt
FlippitTikTokLive.egg-info/requires.txt
FlippitTikTokLive.egg-info/top_level.txt
FlippitTikTokLive/client/__init__.py
FlippitTikTokLive/client/base.py
FlippitTikTokLive/client/client.py
FlippitTikTokLive/client/config.py
FlippitTikTokLive/client/httpx.py
FlippitTikTokLive/client/wsclient.py
FlippitTikTokLive/proto/__init__.py
FlippitTikTokLive/proto/tiktok_schema_pb2.py
FlippitTikTokLive/proto/utilities.py
FlippitTikTokLive/types/__init__.py
FlippitTikTokLive/types/errors.py
FlippitTikTokLive/types/events.py
FlippitTikTokLive/types/objects.py
FlippitTikTokLive/types/utilities.py