Metadata-Version: 2.1
Name: FlippitTikTokLive
Version: 0.2
Summary: Flippit TikTok Live Connection Client
Home-page: https://gitlab.com/flippit/tiktokliveclientfork
Author: Flippit SAS
Author-email: arthur@flippit.ai
License: MIT
Keywords: tiktok,tiktok live,python3,api,unofficial
Classifier: Development Status :: 4 - Beta
Classifier: Intended Audience :: Developers
Classifier: Topic :: Software Development :: Build Tools
Classifier: License :: OSI Approved :: MIT License
Classifier: Natural Language :: English
Classifier: Programming Language :: Python :: 3.7
Classifier: Programming Language :: Python :: 3.8
Classifier: Programming Language :: Python :: 3.9
Classifier: Programming Language :: Python :: 3.10
Classifier: Programming Language :: Python :: 3.11
License-File: LICENSE
Requires-Dist: httpx>=0.23.0
Requires-Dist: protobuf3-to-dict>=0.1.5
Requires-Dist: protobuf>=3.19.4
Requires-Dist: pyee>=9.0.4
Requires-Dist: ffmpy>=0.3.0
Requires-Dist: mashumaro>=3.5
Requires-Dist: websockets>=10.4
